{
    "team_id": 18,
    "team_key": "manchester_city",
    "team_name": "Manchester City",
    "season_id": 4,
    "season": "2019_2020",
    "matches_played": 38,
    "wins": 26,
    "draws": 3,
    "losses": 9,
    "points": 81,
    "goals_for": 102,
    "goals_against": 35,
    "goal_difference": 67,
    "clean_sheets": 17,
    "failed_to_score": 4,
    "home_matches": 19,
    "away_matches": 19,
    "home_wins": 15,
    "home_draws": 2,
    "home_losses": 2,
    "away_wins": 11,
    "away_draws": 1,
    "away_losses": 7,
    "home_goals_for": 57,
    "home_goals_against": 13,
    "away_goals_for": 45,
    "away_goals_against": 22,
    "form": "LWWDW",
    "averages": {
        "ball_possession": 0.6681578947368422,
        "goal_attempts": 19.605263157894736,
        "shots_on_goal": 6.973684210526316,
        "shots_off_goal": 6.7894736842105265,
        "corner_kicks": 7.842105263157895,
        "offsides": 1.8157894736842106,
        "fouls": 9.526315789473685,
        "goalkeeper_saves": 2.1052631578947367,
        "blocked_shots": 5.842105263157895,
        "free_kicks": 10.052631578947368,
        "yellow_cards": 1.7777777777777777,
        "passes_completed": 190.10526315789474,
        "passes_attempted": 691.2105263157895,
        "pass_accuracy": 0.30131578947368426,
        "shot_accuracy": 0.36616995395399066,
        "goal_efficiency": 0.14258176793176833,
        "conversion_rate": 0.37963374344953293,
        "red_cards": 0.8
    },
    "mins": {
        "ball_possession": 0.38,
        "goal_attempts": 7,
        "shots_on_goal": 2,
        "shots_off_goal": 3,
        "corner_kicks": 1,
        "offsides": 0,
        "fouls": 3,
        "goalkeeper_saves": 0,
        "blocked_shots": 0,
        "free_kicks": 5,
        "yellow_cards": 0,
        "passes_completed": 0,
        "passes_attempted": 350,
        "pass_accuracy": 0.0,
        "shot_accuracy": 0.1111111111111111,
        "goal_efficiency": 0.0,
        "conversion_rate": 0.0,
        "red_cards": 0
    },
    "maxes": {
        "ball_possession": 0.78,
        "goal_attempts": 31,
        "shots_on_goal": 12,
        "shots_off_goal": 13,
        "corner_kicks": 17,
        "offsides": 5,
        "fouls": 24,
        "goalkeeper_saves": 8,
        "blocked_shots": 13,
        "free_kicks": 18,
        "yellow_cards": 5,
        "passes_completed": 655,
        "passes_attempted": 891,
        "pass_accuracy": 0.91,
        "shot_accuracy": 0.6428571428571429,
        "goal_efficiency": 0.35714285714285715,
        "conversion_rate": 0.7272727272727273,
        "red_cards": 1
    },
    "points_per_game": 2.1315789473684212,
    "win_percentage": 68.42105263157895,
    "home_win_percentage": 78.94736842105263,
    "away_win_percentage": 57.89473684210527,
    "shot_accuracy_season": 0.36616995395399066,
    "pass_accuracy_season": 0.30131578947368426
}